[{"roomInventory":[{"roomId":0,"inventoryId":2,"quantity":2},{"roomId":0,"inventoryId":0,"quantity":1},{"roomId":0,"inventoryId":3,"quantity":6},{"roomId":0,"inventoryId":4,"quantity":5}],"RoomId":0,"Floor":11,"Occupancy":false,"Purpose":0,"Capacity":10},{"roomInventory":[{"roomId":2,"inventoryId":1,"quantity":2},{"roomId":2,"inventoryId":0,"quantity":2},{"roomId":2,"inventoryId":2,"quantity":1},{"roomId":0,"inventoryId":2,"quantity":1},{"roomId":2,"inventoryId":3,"quantity":3},{"roomId":2,"inventoryId":3,"quantity":1}],"RoomId":2,"Floor":2,"Occupancy":false,"Purpose":1,"Capacity":10},{"roomInventory":[{"roomId":1,"inventoryId":0,"quantity":1},{"roomId":1,"inventoryId":0,"quantity":1},{"roomId":1,"inventoryId":3,"quantity":9},{"roomId":1,"inventoryId":0,"quantity":1},{"roomId":1,"inventoryId":1,"quantity":1},{"roomId":1,"inventoryId":1,"quantity":1},{"roomId":1,"inventoryId":4,"quantity":3}],"RoomId":1,"Floor":4,"Occupancy":false,"Purpose":0,"Capacity":0}]